rubberize/__init__.py
rubberize/config.py
rubberize/exceptions.py
rubberize/export_notebook.py
rubberize/load_ipython_extension.py
rubberize/magics.py
rubberize/utils.py
rubberize/latexer/__init__.py
rubberize/latexer/expr_latex.py
rubberize/latexer/expr_modes.py
rubberize/latexer/expr_rules.py
rubberize/latexer/formatters.py
rubberize/latexer/latex_patterns.py
rubberize/latexer/latexer.py
rubberize/latexer/node_helpers.py
rubberize/latexer/ranks.py
rubberize/latexer/stmt_latex.py
rubberize/latexer/calls/__init__.py
rubberize/latexer/calls/builtin_calls.py
rubberize/latexer/calls/common.py
rubberize/latexer/calls/convert_call.py
rubberize/latexer/calls/numpy_calls.py
rubberize/latexer/calls/pint_calls.py
rubberize/latexer/calls/sympy_calls.py
rubberize/latexer/components/calcsheet.py
rubberize/latexer/components/table.py
rubberize/latexer/node_visitors/__init__.py
rubberize/latexer/node_visitors/expr_visitor.py
rubberize/latexer/node_visitors/mod_visitor.py
rubberize/latexer/node_visitors/stmt_visitor.py
rubberize/latexer/objects/__init__.py
rubberize/latexer/objects/builtin_objects.py
rubberize/latexer/objects/convert_object.py
rubberize/latexer/objects/numpy_objects.py
rubberize/latexer/objects/pint_objects.py
rubberize/latexer/objects/sympy_objects.py
rubberize/render/__init__.py
rubberize/render/render.py
rubberize/render/md_extensions/alert.py
rubberize/render/md_extensions/irbz.py
rubberize/render/md_extensions/latex_linebreak.py
rubberize/render/md_extensions/small.py
rubberize/static/styles.css
rubberize/vendor/ast_comments.py
rubberize-0.3.3.dist-info/licenses/LICENSE
rubberize-0.3.3.dist-info/METADATA
rubberize-0.3.3.dist-info/WHEEL
rubberize-0.3.3.dist-info/top_level.txt
rubberize-0.3.3.dist-info/RECORD
