Metadata-Version: 2.4
Name: rubberize
Version: 0.3.3
Summary: Turn Python calculations into well-formatted, math-rich documents.
Author-email: Chito Peralta <chitoangeloperalta@gmail.com>
License-Expression: MIT
Project-URL: Homepage, https://github.com/chitoperalta/rubberize
Project-URL: Repository, https://github.com/chitoperalta/rubberize
Project-URL: Documentation, https://github.com/chitoperalta/rubberize/blob/main/docs/index.md
Keywords: latex,markdown,jupyter,notebook,math,engineering
Classifier: Development Status :: 4 - Beta
Classifier: Framework :: IPython
Classifier: Framework :: Jupyter
Classifier: Intended Audience :: Science/Research
Classifier: Intended Audience :: Education
Classifier: Intended Audience :: Developers
Classifier: Natural Language :: English
Classifier: Operating System :: OS Independent
Classifier: Programming Language :: Python
Classifier: Programming Language :: Python :: 3
Classifier: Programming Language :: Python :: 3.11
Classifier: Programming Language :: Python :: 3.12
Classifier: Topic :: Education
Classifier: Topic :: Education :: Computer Aided Instruction (CAI)
Classifier: Topic :: Scientific/Engineering
Classifier: Topic :: Scientific/Engineering :: Mathematics
Classifier: Topic :: Software Development :: Documentation
Classifier: Topic :: Text Processing :: Markup :: LaTeX
Classifier: Topic :: Text Processing :: Markup :: Markdown
Classifier: Typing :: Typed
Requires-Python: >=3.11
License-File: LICENSE
Requires-Dist: markdown<4.0,>=3.7
Requires-Dist: titlecase<3.0.0,>=2.4.1
Provides-Extra: notebook
Requires-Dist: ipython<10.0.0,>=9.0.2; extra == "notebook"
Requires-Dist: playwright<2.0.0,>=1.51.0; extra == "notebook"
Requires-Dist: nbconvert<8.0.0,>=7.16.6; extra == "notebook"
Provides-Extra: dev
Requires-Dist: ipython<10.0.0,>=9.0.2; extra == "dev"
Requires-Dist: playwright<2.0.0,>=1.51.0; extra == "dev"
Requires-Dist: nbconvert<8.0.0,>=7.16.6; extra == "dev"
Requires-Dist: jupyterlab<5.0.0,>=4.3.6; extra == "dev"
Requires-Dist: pint<0.25.0,>=0.24.4; extra == "dev"
Requires-Dist: sympy<2.0.0,>=1.13.3; extra == "dev"
Requires-Dist: numpy<3.0.0,>=2.2.4; extra == "dev"
Requires-Dist: pytest<9.0.0,>=8.3.5; extra == "dev"
Dynamic: license-file
